{
  "1": "General",
  "17": "1",
  "51": "2",
  "231": "Building hosting service",
  "232": "X updates",
  "290": "Working on the onboarding flow",
  "348": "Build x follower increase",
  "624": "Damm X posting skill",
  "767": "Ampere.SHJ",
  "807": "3",
  "1079": "OpenClaw use cases",
  "1097": "Money",
  "1174": "Linked Automation",
  "1478": "4",
  "1508": "5",
  "1892": "Landing Amepere",
  "2180": "Auto improve",
  "2410": "Landing specs",
  "2415": "Feature finalize",
  "2476": "Ampere ICP",
  "2485": "Ampere general",
  "2953": "Ampere dashboard",
  "2984": "Landing ampere 2",
  "2988": "landing page 3",
  "3027": "Landing FAQ",
  "3112": "Ampere CTA",
  "3307": "Features sections",
  "3472": "Ampere Uses",
  "3852": "6",
  "3903": "X account research"
}